mc6470/__init__.py
mc6470/mc6470.py
python_MC6470-0.0.8.dist-info/LICENSE
python_MC6470-0.0.8.dist-info/METADATA
python_MC6470-0.0.8.dist-info/WHEEL
python_MC6470-0.0.8.dist-info/top_level.txt
python_MC6470-0.0.8.dist-info/RECORD
