Metadata-Version: 2.1
Name: python-MC6470
Version: 0.0.8
Summary: A python library for accessing MC6470 6-axis accelerometer from mCube via python-smbus using the I2C interface.
Home-page: https://github.com/M-TarunKumar/python-MC6470
Author: Mudige Tarun kumar
Author-email: tarun.mtky@gmail.com
License: UNKNOWN
Platform: UNKNOWN
Classifier: Programming Language :: Python :: 3
Classifier: License :: OSI Approved :: MIT License
Requires-Python: >=3.7
Requires-Dist: smbus
